LICENSE
MANIFEST.in
README.md
setup.py
django_easytz.egg-info/PKG-INFO
django_easytz.egg-info/SOURCES.txt
django_easytz.egg-info/dependency_links.txt
django_easytz.egg-info/not-zip-safe
django_easytz.egg-info/requires.txt
django_easytz.egg-info/top_level.txt
easytz/__init__.py
easytz/middleware.py
easytz/models.py
easytz/tests.py
easytz/static/easytz/js/easytz.js