Metadata-Version: 1.1
Name: django-easytz
Version: 0.3
Summary: Timezone localization without any thinking or doing whatsoever.
Home-page: https://github.com/jamesmfriedman/django-easytz/
Author: James Friedman
Author-email: jamesmfriedman@gmail.com
License: Apache
Download-URL: https://github.com/jamesmfriedman/django-easytz/
Keywords: timezone,tzinfo,datetime,jamesmfriedman,time,django,django-timezones,django-tz,django-easytz
Platform: UNKNOWN
